pydra/tasks/bids/__init__.py
pydra/tasks/bids/utils.py
pydra/tasks/bids/tests/test_utils.py
pydra_bids-0.0.10.dist-info/METADATA
pydra_bids-0.0.10.dist-info/WHEEL
pydra_bids-0.0.10.dist-info/licenses/LICENSE
pydra_bids-0.0.10.dist-info/RECORD
