Metadata-Version: 2.1
Name: pydra-bids
Version: 0.0.10
Summary: Pydra tasks for BIDS I/O
Project-URL: documentation, https://aramis-lab.github.io/pydra-bids
Project-URL: issues, https://github.com/aramis-lab/pydra-bids/issues
Project-URL: repository, https://github.com/aramis-lab/pydra-bids
Author-email: Ghislain Vaillant <ghislain.vaillant@icm-institute.org>
License-Expression: Apache-2.0
License-File: LICENSE
Keywords: bids,neuroimaging,pydra
Classifier: Development Status :: 3 - Alpha
Classifier: Intended Audience :: Science/Research
Classifier: License :: OSI Approved :: Apache Software License
Classifier: Operating System :: OS Independent
Classifier: Programming Language :: Python :: 3
Classifier: Programming Language :: Python :: 3.7
Classifier: Programming Language :: Python :: 3.8
Classifier: Programming Language :: Python :: 3.9
Classifier: Programming Language :: Python :: 3.10
Classifier: Programming Language :: Python :: 3.11
Classifier: Topic :: Scientific/Engineering
Classifier: Topic :: Software Development :: Libraries
Requires-Python: >=3.7
Requires-Dist: ancpbids<0.3,>=0.2
Requires-Dist: pydra>=0.21
